<annotation>
	<folder>FFPMask</folder>
	<filename>Pic_1383.jpg</filename>
	<path>C:\Users\Dehmane\PycharmProjects\Real-time-object-detection\Dataset\Images\Train\FFPMask\Pic_1383.jpg</path>
	<source>
		<database>Unknown</database>
	</source>
	<size>
		<width>400</width>
		<height>400</height>
		<depth>3</depth>
	</size>
	<segmented>0</segmented>
	<object>
		<name>FFPMask</name>
		<pose>Unspecified</pose>
		<truncated>0</truncated>
		<difficult>0</difficult>
		<bndbox>
			<xmin>239</xmin>
			<ymin>114</ymin>
			<xmax>376</xmax>
			<ymax>227</ymax>
		</bndbox>
	</object>
</annotation>
